reahl/swordfish/__init__.py
reahl/swordfish/main.py
reahl_swordfish-0.1.1.dist-info/licenses/LICENSE
reahl_swordfish-0.1.1.dist-info/METADATA
reahl_swordfish-0.1.1.dist-info/WHEEL
reahl_swordfish-0.1.1.dist-info/entry_points.txt
reahl_swordfish-0.1.1.dist-info/top_level.txt
reahl_swordfish-0.1.1.dist-info/RECORD
