Metadata-Version: 2.4
Name: reahl-swordfish
Version: 0.1.1
Summary: A classic Smalltalk IDE for GemStone/Smalltalk
Author-email: "Reahl Software Services (Pty) Ltd" <info@reahl.org>
License: GPL-3.0-or-later
Project-URL: Homepage, https://github.com/reahl/swordfish
Project-URL: Bug Tracker, https://github.com/reahl/swordfish/issues
Keywords: smalltalk,gemstone,ide,development
Classifier: Development Status :: 3 - Alpha
Classifier: Intended Audience :: Developers
Classifier: License :: OSI Approved :: GNU General Public License v3 or later (GPLv3+)
Classifier: Programming Language :: Python :: 3
Classifier: Programming Language :: Python :: 3.6
Classifier: Programming Language :: Python :: 3.7
Classifier: Programming Language :: Python :: 3.8
Classifier: Programming Language :: Python :: 3.9
Classifier: Programming Language :: Python :: 3.10
Classifier: Topic :: Software Development
Requires-Python: >=3.6
License-File: LICENSE
Requires-Dist: reahl-parseltongue
Dynamic: license-file
